{"observations":[{"stationID":"ISTGBUCH2","tz":"Europe/London","obsTimeUtc":"2020-01-12T23:59:52Z","obsTimeLocal":"2020-01-12 23:59:52","epoch":1578873592,"lat":56.11800003,"lon":-4.30164814,"solarRadiationHigh":161.7,"uvHigh":1.0,"winddirAvg":273,"humidityHigh":93.0,"humidityLow":78.0,"humidityAvg":88.3,"qcStatus":1,"metric":{"tempHigh":7.4,"tempLow":3.0,"tempAvg":4.5,"windspeedHigh":15.4,"windspeedLow":0.0,"windspeedAvg":4.1,"windgustHigh":20.1,"windgustLow":0.0,"windgustAvg":5.7,"dewptHigh":4.9,"dewptLow":1.6,"dewptAvg":2.7,"windchillHigh":7.4,"windchillLow":-0.5,"windchillAvg":4.0,"heatindexHigh":7.4,"heatindexLow":3.0,"heatindexAvg":4.5,"pressureMax":1006.77,"pressureMin":1002.37,"pressureTrend":-0.06,"precipRate":3.05,"precipTotal":1.27}}]}
