{"observations":[{"stationID":"ISTGBUCH2","tz":"Europe/London","obsTimeUtc":"2021-03-20T23:59:53Z","obsTimeLocal":"2021-03-20 23:59:53","epoch":1616284793,"lat":56.118,"lon":-4.301648,"solarRadiationHigh":614.6,"uvHigh":5.0,"winddirAvg":289,"humidityHigh":99.0,"humidityLow":66.0,"humidityAvg":85.9,"qcStatus":0,"metric":{"tempHigh":13.9,"tempLow":2.0,"tempAvg":8.4,"windspeedHigh":21.6,"windspeedLow":0.0,"windspeedAvg":5.4,"windgustHigh":33.2,"windgustLow":0.0,"windgustAvg":7.1,"dewptHigh":9.2,"dewptLow":1.6,"dewptAvg":6.1,"windchillHigh":13.9,"windchillLow":2.0,"windchillAvg":8.2,"heatindexHigh":13.9,"heatindexLow":2.0,"heatindexAvg":8.4,"pressureMax":1028.72,"pressureMin":1024.11,"pressureTrend":-0.10,"precipRate":0.00,"precipTotal":0.00}}]}
