{"observations":[{"stationID":"ISTGBUCH2","tz":"Europe/London","obsTimeUtc":"2020-05-29T22:59:46Z","obsTimeLocal":"2020-05-29 23:59:46","epoch":1590793186,"lat":56.118,"lon":-4.301648,"solarRadiationHigh":759.6,"uvHigh":7.0,"winddirAvg":15,"humidityHigh":97.0,"humidityLow":41.0,"humidityAvg":71.0,"qcStatus":0,"metric":{"tempHigh":27.2,"tempLow":7.6,"tempAvg":17.7,"windspeedHigh":9.7,"windspeedLow":0.0,"windspeedAvg":1.2,"windgustHigh":13.0,"windgustLow":0.0,"windgustAvg":1.8,"dewptHigh":16.1,"dewptLow":7.1,"dewptAvg":11.6,"windchillHigh":27.2,"windchillLow":7.6,"windchillAvg":17.7,"heatindexHigh":27.4,"heatindexLow":7.6,"heatindexAvg":17.6,"pressureMax":1025.74,"pressureMin":1020.32,"pressureTrend":-0.17,"precipRate":0.00,"precipTotal":0.00}}]}
