{"observations":[{"stationID":"ISTGBUCH2","tz":"Europe/London","obsTimeUtc":"2021-08-10T22:59:45Z","obsTimeLocal":"2021-08-10 23:59:45","epoch":1628636385,"lat":56.118,"lon":-4.301648,"solarRadiationHigh":921.0,"uvHigh":8.0,"winddirAvg":333,"humidityHigh":99.0,"humidityLow":66.0,"humidityAvg":88.0,"qcStatus":0,"metric":{"tempHigh":22.3,"tempLow":8.0,"tempAvg":14.6,"windspeedHigh":13.7,"windspeedLow":0.0,"windspeedAvg":1.1,"windgustHigh":16.6,"windgustLow":0.0,"windgustAvg":1.5,"dewptHigh":17.2,"dewptLow":7.8,"dewptAvg":12.5,"windchillHigh":22.3,"windchillLow":8.0,"windchillAvg":14.6,"heatindexHigh":22.5,"heatindexLow":8.0,"heatindexAvg":14.6,"pressureMax":1010.23,"pressureMin":1005.11,"pressureTrend":0.19,"precipRate":0.00,"precipTotal":0.00}}]}
