{"observations":[{"stationID":"ISTGBUCH2","tz":"Europe/London","obsTimeUtc":"2021-01-17T00:59:52Z","obsTimeLocal":"2021-01-17 00:59:52","epoch":1610845192,"lat":56.118,"lon":-4.301648,"solarRadiationHigh":0.0,"uvHigh":0.0,"winddirAvg":280,"humidityHigh":89.0,"humidityLow":87.0,"humidityAvg":88.1,"qcStatus":1,"metric":{"tempHigh":4.2,"tempLow":3.8,"tempAvg":4.0,"windspeedHigh":10.5,"windspeedLow":1.4,"windspeedAvg":4.4,"windgustHigh":16.6,"windgustLow":1.8,"windgustAvg":6.4,"dewptHigh":2.3,"dewptLow":1.9,"dewptAvg":2.1,"windchillHigh":4.2,"windchillLow":1.1,"windchillAvg":3.4,"heatindexHigh":4.2,"heatindexLow":3.8,"heatindexAvg":4.0,"pressureMax":1009.62,"pressureMin":1008.43,"pressureTrend":0.78,"precipRate":0.00,"precipTotal":0.00}},{"stationID":"ISTGBUCH2","tz":"Europe/London","obsTimeUtc":"2021-01-17T01:59:52Z","obsTimeLocal":"2021-01-17 01:59:52","epoch":1610848792,"lat":56.118,"lon":-4.301648,"solarRadiationHigh":0.0,"uvHigh":0.0,"winddirAvg":280,"humidityHigh":89.0,"humidityLow":87.0,"humidityAvg":88.4,"qcStatus":1,"metric":{"tempHigh":4.1,"tempLow":3.4,"tempAvg":3.8,"windspeedHigh":12.2,"windspeedLow":0.3,"windspeedAvg":4.0,"windgustHigh":20.1,"windgustLow":1.8,"windgustAvg":5.8,"dewptHigh":2.2,"dewptLow":1.7,"dewptAvg":2.0,"windchillHigh":4.1,"windchillLow":1.0,"windchillAvg":3.5,"heatindexHigh":4.1,"heatindexLow":3.4,"heatindexAvg":3.8,"pressureMax":1009.92,"pressureMin":1009.31,"pressureTrend":0.31,"precipRate":0.00,"precipTotal":0.00}},{"stationID":"ISTGBUCH2","tz":"Europe/London","obsTimeUtc":"2021-01-17T02:59:52Z","obsTimeLocal":"2021-01-17 02:59:52","epoch":1610852392,"lat":56.118,"lon":-4.301648,"solarRadiationHigh":0.0,"uvHigh":0.0,"winddirAvg":274,"humidityHigh":91.0,"humidityLow":88.0,"humidityAvg":88.9,"qcStatus":1,"metric":{"tempHigh":4.0,"tempLow":2.2,"tempAvg":3.4,"windspeedHigh":9.3,"windspeedLow":0.0,"windspeedAvg":3.1,"windgustHigh":14.8,"windgustLow":0.0,"windgustAvg":4.6,"dewptHigh":2.1,"dewptLow":0.8,"dewptAvg":1.7,"windchillHigh":4.0,"windchillLow":0.8,"windchillAvg":3.2,"heatindexHigh":4.0,"heatindexLow":2.2,"heatindexAvg":3.4,"pressureMax":1010.63,"pressureMin":1009.72,"pressureTrend":0.41,"precipRate":0.00,"precipTotal":0.00}},{"stationID":"ISTGBUCH2","tz":"Europe/London","obsTimeUtc":"2021-01-17T03:59:52Z","obsTimeLocal":"2021-01-17 03:59:52","epoch":1610855992,"lat":56.118,"lon":-4.301648,"solarRadiationHigh":0.0,"uvHigh":0.0,"winddirAvg":294,"humidityHigh":92.0,"humidityLow":82.0,"humidityAvg":86.0,"qcStatus":1,"metric":{"tempHigh":5.1,"tempLow":2.1,"tempAvg":3.8,"windspeedHigh":9.3,"windspeedLow":0.0,"windspeedAvg":3.4,"windgustHigh":13.0,"windgustLow":0.0,"windgustAvg":4.6,"dewptHigh":2.4,"dewptLow":0.8,"dewptAvg":1.6,"windchillHigh":5.1,"windchillLow":0.7,"windchillAvg":3.4,"heatindexHigh":5.1,"heatindexLow":2.1,"heatindexAvg":3.8,"pressureMax":1011.41,"pressureMin":1010.23,"pressureTrend":0.99,"precipRate":0.00,"precipTotal":0.00}},{"stationID":"ISTGBUCH2","tz":"Europe/London","obsTimeUtc":"2021-01-17T04:59:52Z","obsTimeLocal":"2021-01-17 04:59:52","epoch":1610859592,"lat":56.118,"lon":-4.301648,"solarRadiationHigh":0.0,"uvHigh":0.0,"winddirAvg":284,"humidityHigh":90.0,"humidityLow":83.0,"humidityAvg":87.6,"qcStatus":1,"metric":{"tempHigh":4.4,"tempLow":2.8,"tempAvg":3.4,"windspeedHigh":11.9,"windspeedLow":0.0,"windspeedAvg":3.9,"windgustHigh":16.6,"windgustLow":0.0,"windgustAvg":5.1,"dewptHigh":2.2,"dewptLow":0.9,"dewptAvg":1.5,"windchillHigh":4.3,"windchillLow":0.6,"windchillAvg":2.9,"heatindexHigh":4.4,"heatindexLow":2.8,"heatindexAvg":3.4,"pressureMax":1011.92,"pressureMin":1011.31,"pressureTrend":0.51,"precipRate":0.00,"precipTotal":0.00}},{"stationID":"ISTGBUCH2","tz":"Europe/London","obsTimeUtc":"2021-01-17T05:59:52Z","obsTimeLocal":"2021-01-17 05:59:52","epoch":1610863192,"lat":56.118,"lon":-4.301648,"solarRadiationHigh":0.0,"uvHigh":0.0,"winddirAvg":287,"humidityHigh":89.0,"humidityLow":83.0,"humidityAvg":86.6,"qcStatus":1,"metric":{"tempHigh":4.5,"tempLow":3.0,"tempAvg":3.6,"windspeedHigh":13.0,"windspeedLow":1.8,"windspeedAvg":6.1,"windgustHigh":18.3,"windgustLow":1.8,"windgustAvg":7.5,"dewptHigh":2.0,"dewptLow":1.1,"dewptAvg":1.6,"windchillHigh":4.4,"windchillLow":0.1,"windchillAvg":2.5,"heatindexHigh":4.5,"heatindexLow":3.0,"heatindexAvg":3.6,"pressureMax":1012.53,"pressureMin":1011.82,"pressureTrend":0.61,"precipRate":0.00,"precipTotal":0.00}},{"stationID":"ISTGBUCH2","tz":"Europe/London","obsTimeUtc":"2021-01-17T06:59:52Z","obsTimeLocal":"2021-01-17 06:59:52","epoch":1610866792,"lat":56.118,"lon":-4.301648,"solarRadiationHigh":0.0,"uvHigh":0.0,"winddirAvg":287,"humidityHigh":91.0,"humidityLow":83.0,"humidityAvg":88.0,"qcStatus":1,"metric":{"tempHigh":4.5,"tempLow":2.7,"tempAvg":3.4,"windspeedHigh":12.2,"windspeedLow":4.0,"windspeedAvg":6.7,"windgustHigh":16.6,"windgustLow":5.5,"windgustAvg":8.1,"dewptHigh":2.0,"dewptLow":1.2,"dewptAvg":1.6,"windchillHigh":3.2,"windchillLow":0.4,"windchillAvg":1.8,"heatindexHigh":4.5,"heatindexLow":2.7,"heatindexAvg":3.4,"pressureMax":1013.41,"pressureMin":1012.33,"pressureTrend":0.92,"precipRate":0.00,"precipTotal":0.00}},{"stationID":"ISTGBUCH2","tz":"Europe/London","obsTimeUtc":"2021-01-17T07:59:52Z","obsTimeLocal":"2021-01-17 07:59:52","epoch":1610870392,"lat":56.118,"lon":-4.301648,"solarRadiationHigh":0.0,"uvHigh":0.0,"winddirAvg":284,"humidityHigh":90.0,"humidityLow":82.0,"humidityAvg":86.3,"qcStatus":1,"metric":{"tempHigh":5.0,"tempLow":2.7,"tempAvg":3.9,"windspeedHigh":10.1,"windspeedLow":0.3,"windspeedAvg":5.1,"windgustHigh":16.6,"windgustLow":1.8,"windgustAvg":6.6,"dewptHigh":2.5,"dewptLow":1.2,"dewptAvg":1.8,"windchillHigh":5.0,"windchillLow":1.2,"windchillAvg":3.1,"heatindexHigh":5.0,"heatindexLow":2.7,"heatindexAvg":3.9,"pressureMax":1014.12,"pressureMin":1012.94,"pressureTrend":0.78,"precipRate":0.00,"precipTotal":0.00}},{"stationID":"ISTGBUCH2","tz":"Europe/London","obsTimeUtc":"2021-01-17T08:59:52Z","obsTimeLocal":"2021-01-17 08:59:52","epoch":1610873992,"lat":56.118,"lon":-4.301648,"solarRadiationHigh":6.9,"uvHigh":0.0,"winddirAvg":270,"humidityHigh":88.0,"humidityLow":85.0,"humidityAvg":86.3,"qcStatus":1,"metric":{"tempHigh":4.6,"tempLow":3.7,"tempAvg":4.1,"windspeedHigh":12.6,"windspeedLow":0.3,"windspeedAvg":4.8,"windgustHigh":18.3,"windgustLow":1.8,"windgustAvg":7.1,"dewptHigh":2.3,"dewptLow":1.7,"dewptAvg":2.0,"windchillHigh":4.5,"windchillLow":0.7,"windchillAvg":3.4,"heatindexHigh":4.6,"heatindexLow":3.7,"heatindexAvg":4.1,"pressureMax":1014.93,"pressureMin":1013.82,"pressureTrend":0.61,"precipRate":0.00,"precipTotal":0.00}},{"stationID":"ISTGBUCH2","tz":"Europe/London","obsTimeUtc":"2021-01-17T09:59:53Z","obsTimeLocal":"2021-01-17 09:59:53","epoch":1610877593,"lat":56.118,"lon":-4.301648,"solarRadiationHigh":26.4,"uvHigh":0.0,"winddirAvg":276,"humidityHigh":88.0,"humidityLow":86.0,"humidityAvg":87.1,"qcStatus":1,"metric":{"tempHigh":4.6,"tempLow":3.9,"tempAvg":4.2,"windspeedHigh":9.7,"windspeedLow":0.6,"windspeedAvg":4.0,"windgustHigh":16.6,"windgustLow":1.8,"windgustAvg":6.0,"dewptHigh":2.7,"dewptLow":1.8,"dewptAvg":2.2,"windchillHigh":4.6,"windchillLow":1.9,"windchillAvg":3.8,"heatindexHigh":4.6,"heatindexLow":3.9,"heatindexAvg":4.2,"pressureMax":1015.24,"pressureMin":1014.33,"pressureTrend":0.41,"precipRate":0.00,"precipTotal":0.00}},{"stationID":"ISTGBUCH2","tz":"Europe/London","obsTimeUtc":"2021-01-17T10:59:53Z","obsTimeLocal":"2021-01-17 10:59:53","epoch":1610881193,"lat":56.118,"lon":-4.301648,"solarRadiationHigh":47.7,"uvHigh":0.0,"winddirAvg":266,"humidityHigh":92.0,"humidityLow":87.0,"humidityAvg":88.4,"qcStatus":1,"metric":{"tempHigh":5.1,"tempLow":4.6,"tempAvg":4.9,"windspeedHigh":12.6,"windspeedLow":1.4,"windspeedAvg":5.0,"windgustHigh":20.1,"windgustLow":1.8,"windgustAvg":7.9,"dewptHigh":3.7,"dewptLow":2.6,"dewptAvg":3.1,"windchillHigh":5.1,"windchillLow":2.0,"windchillAvg":4.2,"heatindexHigh":5.1,"heatindexLow":4.6,"heatindexAvg":4.9,"pressureMax":1015.71,"pressureMin":1014.73,"pressureTrend":0.58,"precipRate":1.80,"precipTotal":0.30}},{"stationID":"ISTGBUCH2","tz":"Europe/London","obsTimeUtc":"2021-01-17T11:59:53Z","obsTimeLocal":"2021-01-17 11:59:53","epoch":1610884793,"lat":56.118,"lon":-4.301648,"solarRadiationHigh":53.3,"uvHigh":0.0,"winddirAvg":271,"humidityHigh":93.0,"humidityLow":89.0,"humidityAvg":91.4,"qcStatus":1,"metric":{"tempHigh":5.2,"tempLow":4.6,"tempAvg":4.8,"windspeedHigh":16.9,"windspeedLow":0.0,"windspeedAvg":5.2,"windgustHigh":23.8,"windgustLow":0.0,"windgustAvg":8.1,"dewptHigh":3.6,"dewptLow":3.4,"dewptAvg":3.5,"windchillHigh":5.2,"windchillLow":1.3,"windchillAvg":4.1,"heatindexHigh":5.2,"heatindexLow":4.6,"heatindexAvg":4.8,"pressureMax":1015.71,"pressureMin":1014.83,"pressureTrend":-0.68,"precipRate":0.00,"precipTotal":0.30}},{"stationID":"ISTGBUCH2","tz":"Europe/London","obsTimeUtc":"2021-01-17T12:59:53Z","obsTimeLocal":"2021-01-17 12:59:53","epoch":1610888393,"lat":56.118,"lon":-4.301648,"solarRadiationHigh":106.2,"uvHigh":1.0,"winddirAvg":262,"humidityHigh":90.0,"humidityLow":86.0,"humidityAvg":87.9,"qcStatus":1,"metric":{"tempHigh":6.6,"tempLow":5.1,"tempAvg":6.0,"windspeedHigh":14.3,"windspeedLow":0.6,"windspeedAvg":5.2,"windgustHigh":16.6,"windgustLow":1.8,"windgustAvg":7.5,"dewptHigh":4.6,"dewptLow":3.4,"dewptAvg":4.1,"windchillHigh":6.6,"windchillLow":2.1,"windchillAvg":5.3,"heatindexHigh":6.6,"heatindexLow":5.1,"heatindexAvg":6.0,"pressureMax":1015.34,"pressureMin":1014.63,"pressureTrend":-0.20,"precipRate":0.00,"precipTotal":0.30}},{"stationID":"ISTGBUCH2","tz":"Europe/London","obsTimeUtc":"2021-01-17T13:59:53Z","obsTimeLocal":"2021-01-17 13:59:53","epoch":1610891993,"lat":56.118,"lon":-4.301648,"solarRadiationHigh":137.0,"uvHigh":1.0,"winddirAvg":283,"humidityHigh":88.0,"humidityLow":85.0,"humidityAvg":86.3,"qcStatus":1,"metric":{"tempHigh":6.9,"tempLow":6.5,"tempAvg":6.7,"windspeedHigh":17.7,"windspeedLow":2.1,"windspeedAvg":5.5,"windgustHigh":23.8,"windgustLow":3.5,"windgustAvg":7.0,"dewptHigh":4.7,"dewptLow":4.3,"dewptAvg":4.6,"windchillHigh":6.9,"windchillLow":3.2,"windchillAvg":6.0,"heatindexHigh":6.9,"heatindexLow":6.5,"heatindexAvg":6.7,"pressureMax":1014.93,"pressureMin":1013.92,"pressureTrend":-0.71,"precipRate":0.00,"precipTotal":0.30}},{"stationID":"ISTGBUCH2","tz":"Europe/London","obsTimeUtc":"2021-01-17T14:59:53Z","obsTimeLocal":"2021-01-17 14:59:53","epoch":1610895593,"lat":56.118,"lon":-4.301648,"solarRadiationHigh":75.8,"uvHigh":0.0,"winddirAvg":279,"humidityHigh":94.0,"humidityLow":88.0,"humidityAvg":91.0,"qcStatus":1,"metric":{"tempHigh":6.7,"tempLow":6.2,"tempAvg":6.5,"windspeedHigh":10.1,"windspeedLow":1.4,"windspeedAvg":4.9,"windgustHigh":20.1,"windgustLow":1.8,"windgustAvg":6.7,"dewptHigh":5.3,"dewptLow":4.7,"dewptAvg":5.1,"windchillHigh":6.7,"windchillLow":4.7,"windchillAvg":5.9,"heatindexHigh":6.7,"heatindexLow":6.2,"heatindexAvg":6.5,"pressureMax":1014.33,"pressureMin":1013.51,"pressureTrend":-0.61,"precipRate":1.80,"precipTotal":0.79}},{"stationID":"ISTGBUCH2","tz":"Europe/London","obsTimeUtc":"2021-01-17T15:59:53Z","obsTimeLocal":"2021-01-17 15:59:53","epoch":1610899193,"lat":56.118,"lon":-4.301648,"solarRadiationHigh":18.1,"uvHigh":0.0,"winddirAvg":282,"humidityHigh":95.0,"humidityLow":94.0,"humidityAvg":94.7,"qcStatus":1,"metric":{"tempHigh":6.2,"tempLow":6.0,"tempAvg":6.1,"windspeedHigh":11.6,"windspeedLow":1.1,"windspeedAvg":5.9,"windgustHigh":16.6,"windgustLow":1.8,"windgustAvg":7.5,"dewptHigh":5.3,"dewptLow":5.1,"dewptAvg":5.2,"windchillHigh":6.2,"windchillLow":3.7,"windchillAvg":5.2,"heatindexHigh":6.2,"heatindexLow":6.0,"heatindexAvg":6.1,"pressureMax":1013.82,"pressureMin":1013.04,"pressureTrend":-0.17,"precipRate":3.61,"precipTotal":2.31}},{"stationID":"ISTGBUCH2","tz":"Europe/London","obsTimeUtc":"2021-01-17T16:59:53Z","obsTimeLocal":"2021-01-17 16:59:53","epoch":1610902793,"lat":56.118,"lon":-4.301648,"solarRadiationHigh":4.3,"uvHigh":0.0,"winddirAvg":281,"humidityHigh":96.0,"humidityLow":95.0,"humidityAvg":95.1,"qcStatus":1,"metric":{"tempHigh":6.2,"tempLow":6.0,"tempAvg":6.1,"windspeedHigh":10.5,"windspeedLow":2.9,"windspeedAvg":6.2,"windgustHigh":13.0,"windgustLow":3.5,"windgustAvg":7.8,"dewptHigh":5.7,"dewptLow":5.2,"dewptAvg":5.3,"windchillHigh":6.2,"windchillLow":3.8,"windchillAvg":5.0,"heatindexHigh":6.2,"heatindexLow":6.0,"heatindexAvg":6.1,"pressureMax":1013.41,"pressureMin":1012.84,"pressureTrend":0.00,"precipRate":3.00,"precipTotal":3.10}},{"stationID":"ISTGBUCH2","tz":"Europe/London","obsTimeUtc":"2021-01-17T17:59:53Z","obsTimeLocal":"2021-01-17 17:59:53","epoch":1610906393,"lat":56.118,"lon":-4.301648,"solarRadiationHigh":0.0,"uvHigh":0.0,"winddirAvg":278,"humidityHigh":96.0,"humidityLow":95.0,"humidityAvg":95.7,"qcStatus":1,"metric":{"tempHigh":6.1,"tempLow":5.9,"tempAvg":6.0,"windspeedHigh":11.1,"windspeedLow":0.6,"windspeedAvg":4.1,"windgustHigh":14.8,"windgustLow":1.8,"windgustAvg":5.9,"dewptHigh":5.6,"dewptLow":5.1,"dewptAvg":5.4,"windchillHigh":6.1,"windchillLow":3.6,"windchillAvg":5.7,"heatindexHigh":6.1,"heatindexLow":5.9,"heatindexAvg":6.0,"pressureMax":1013.41,"pressureMin":1012.63,"pressureTrend":-0.61,"precipRate":4.80,"precipTotal":4.09}},{"stationID":"ISTGBUCH2","tz":"Europe/London","obsTimeUtc":"2021-01-17T18:59:53Z","obsTimeLocal":"2021-01-17 18:59:53","epoch":1610909993,"lat":56.118,"lon":-4.301648,"solarRadiationHigh":0.0,"uvHigh":0.0,"winddirAvg":284,"humidityHigh":96.0,"humidityLow":94.0,"humidityAvg":95.0,"qcStatus":1,"metric":{"tempHigh":6.3,"tempLow":6.0,"tempAvg":6.2,"windspeedHigh":13.0,"windspeedLow":1.4,"windspeedAvg":6.6,"windgustHigh":16.6,"windgustLow":1.8,"windgustAvg":8.0,"dewptHigh":5.6,"dewptLow":5.2,"dewptAvg":5.4,"windchillHigh":6.2,"windchillLow":3.6,"windchillAvg":5.0,"heatindexHigh":6.3,"heatindexLow":6.0,"heatindexAvg":6.2,"pressureMax":1013.14,"pressureMin":1012.43,"pressureTrend":0.31,"precipRate":4.80,"precipTotal":5.89}},{"stationID":"ISTGBUCH2","tz":"Europe/London","obsTimeUtc":"2021-01-17T19:59:53Z","obsTimeLocal":"2021-01-17 19:59:53","epoch":1610913593,"lat":56.118,"lon":-4.301648,"solarRadiationHigh":0.0,"uvHigh":0.0,"winddirAvg":289,"humidityHigh":95.0,"humidityLow":91.0,"humidityAvg":92.8,"qcStatus":1,"metric":{"tempHigh":6.1,"tempLow":5.7,"tempAvg":6.0,"windspeedHigh":13.0,"windspeedLow":3.2,"windspeedAvg":7.4,"windgustHigh":18.3,"windgustLow":3.5,"windgustAvg":9.3,"dewptHigh":5.3,"dewptLow":4.5,"dewptAvg":4.8,"windchillHigh":6.1,"windchillLow":3.0,"windchillAvg":4.6,"heatindexHigh":6.1,"heatindexLow":5.7,"heatindexAvg":6.0,"pressureMax":1013.24,"pressureMin":1012.53,"pressureTrend":-0.20,"precipRate":4.80,"precipTotal":7.90}},{"stationID":"ISTGBUCH2","tz":"Europe/London","obsTimeUtc":"2021-01-17T20:59:53Z","obsTimeLocal":"2021-01-17 20:59:53","epoch":1610917193,"lat":56.118,"lon":-4.301648,"solarRadiationHigh":0.0,"uvHigh":0.0,"winddirAvg":286,"humidityHigh":95.0,"humidityLow":93.0,"humidityAvg":94.1,"qcStatus":1,"metric":{"tempHigh":5.7,"tempLow":5.4,"tempAvg":5.5,"windspeedHigh":10.5,"windspeedLow":1.4,"windspeedAvg":5.6,"windgustHigh":18.3,"windgustLow":1.8,"windgustAvg":7.0,"dewptHigh":4.7,"dewptLow":4.4,"dewptAvg":4.6,"windchillHigh":5.7,"windchillLow":3.2,"windchillAvg":4.7,"heatindexHigh":5.7,"heatindexLow":5.4,"heatindexAvg":5.5,"pressureMax":1012.94,"pressureMin":1012.02,"pressureTrend":-0.71,"precipRate":5.99,"precipTotal":10.21}},{"stationID":"ISTGBUCH2","tz":"Europe/London","obsTimeUtc":"2021-01-17T21:59:53Z","obsTimeLocal":"2021-01-17 21:59:53","epoch":1610920793,"lat":56.118,"lon":-4.301648,"solarRadiationHigh":0.0,"uvHigh":0.0,"winddirAvg":291,"humidityHigh":98.0,"humidityLow":95.0,"humidityAvg":96.5,"qcStatus":1,"metric":{"tempHigh":5.9,"tempLow":5.2,"tempAvg":5.3,"windspeedHigh":6.4,"windspeedLow":0.0,"windspeedAvg":2.2,"windgustHigh":9.3,"windgustLow":0.0,"windgustAvg":3.2,"dewptHigh":5.5,"dewptLow":4.6,"dewptAvg":4.9,"windchillHigh":5.9,"windchillLow":3.9,"windchillAvg":5.3,"heatindexHigh":5.9,"heatindexLow":5.2,"heatindexAvg":5.3,"pressureMax":1012.33,"pressureMin":1011.41,"pressureTrend":-0.51,"precipRate":4.80,"precipTotal":11.20}},{"stationID":"ISTGBUCH2","tz":"Europe/London","obsTimeUtc":"2021-01-17T22:59:53Z","obsTimeLocal":"2021-01-17 22:59:53","epoch":1610924393,"lat":56.118,"lon":-4.301648,"solarRadiationHigh":0.0,"uvHigh":0.0,"winddirAvg":286,"humidityHigh":97.0,"humidityLow":94.0,"humidityAvg":94.9,"qcStatus":1,"metric":{"tempHigh":6.4,"tempLow":5.9,"tempAvg":6.2,"windspeedHigh":12.2,"windspeedLow":0.3,"windspeedAvg":6.7,"windgustHigh":16.6,"windgustLow":1.8,"windgustAvg":8.4,"dewptHigh":5.7,"dewptLow":5.2,"dewptAvg":5.4,"windchillHigh":6.3,"windchillLow":3.9,"windchillAvg":5.0,"heatindexHigh":6.4,"heatindexLow":5.9,"heatindexAvg":6.2,"pressureMax":1011.72,"pressureMin":1010.84,"pressureTrend":-0.68,"precipRate":4.19,"precipTotal":12.50}},{"stationID":"ISTGBUCH2","tz":"Europe/London","obsTimeUtc":"2021-01-17T23:59:53Z","obsTimeLocal":"2021-01-17 23:59:53","epoch":1610927993,"lat":56.118,"lon":-4.301648,"solarRadiationHigh":0.0,"uvHigh":0.0,"winddirAvg":285,"humidityHigh":95.0,"humidityLow":93.0,"humidityAvg":94.3,"qcStatus":1,"metric":{"tempHigh":6.3,"tempLow":6.0,"tempAvg":6.2,"windspeedHigh":18.7,"windspeedLow":4.0,"windspeedAvg":8.9,"windgustHigh":25.6,"windgustLow":5.5,"windgustAvg":11.1,"dewptHigh":5.5,"dewptLow":5.1,"dewptAvg":5.2,"windchillHigh":6.2,"windchillLow":2.8,"windchillAvg":4.4,"heatindexHigh":6.3,"heatindexLow":6.0,"heatindexAvg":6.2,"pressureMax":1011.31,"pressureMin":1010.13,"pressureTrend":-0.61,"precipRate":3.00,"precipTotal":13.69}}]}
