{"observations":[{"stationID":"ISTGBUCH2","tz":"Europe/London","obsTimeUtc":"2021-04-07T22:46:40Z","obsTimeLocal":"2021-04-07 23:46:40","epoch":1617835600,"lat":56.118,"lon":-4.301648,"solarRadiationHigh":773.9,"uvHigh":7.0,"winddirAvg":307,"humidityHigh":84.0,"humidityLow":44.0,"humidityAvg":68.1,"qcStatus":-1,"metric":{"tempHigh":8.1,"tempLow":-2.4,"tempAvg":1.9,"windspeedHigh":17.2,"windspeedLow":0.0,"windspeedAvg":3.3,"windgustHigh":23.8,"windgustLow":0.0,"windgustAvg":4.4,"dewptHigh":1.0,"dewptLow":-5.3,"dewptAvg":-3.6,"windchillHigh":7.8,"windchillLow":-3.9,"windchillAvg":1.6,"heatindexHigh":8.1,"heatindexLow":-2.4,"heatindexAvg":1.9,"pressureMax":1018.93,"pressureMin":1014.33,"pressureTrend":-0.15,"precipRate":0.00,"precipTotal":0.00}}]}
