{"observations":[{"stationID":"ISTGBUCH2","tz":"Europe/London","obsTimeUtc":"2022-05-17T22:59:47Z","obsTimeLocal":"2022-05-17 23:59:47","epoch":1652828387,"lat":56.118,"lon":-4.301648,"solarRadiationHigh":708.8,"uvHigh":6.0,"winddirAvg":96,"humidityHigh":99.0,"humidityLow":79.0,"humidityAvg":92.2,"qcStatus":1,"metric":{"tempHigh":17.9,"tempLow":8.3,"tempAvg":13.1,"windspeedHigh":13.7,"windspeedLow":0.0,"windspeedAvg":2.5,"windgustHigh":21.9,"windgustLow":0.0,"windgustAvg":3.7,"dewptHigh":14.6,"dewptLow":8.1,"dewptAvg":11.7,"windchillHigh":17.9,"windchillLow":8.3,"windchillAvg":13.1,"heatindexHigh":17.9,"heatindexLow":8.3,"heatindexAvg":13.1,"pressureMax":1010.94,"pressureMin":1000.34,"pressureTrend":-0.18,"precipRate":18.01,"precipTotal":5.59}}]}
