{"observations":[{"stationID":"ISTGBUCH2","tz":"Europe/London","obsTimeUtc":"2021-06-02T23:59:51Z","obsTimeLocal":"2021-06-03 00:59:51","epoch":1622678391,"lat":56.118,"lon":-4.301648,"solarRadiationHigh":0.0,"uvHigh":0.0,"winddirAvg":136,"humidityHigh":92.0,"humidityLow":91.0,"humidityAvg":91.6,"qcStatus":1,"metric":{"tempHigh":10.9,"tempLow":10.7,"tempAvg":10.8,"windspeedHigh":10.8,"windspeedLow":1.1,"windspeedAvg":5.8,"windgustHigh":16.6,"windgustLow":1.8,"windgustAvg":8.2,"dewptHigh":9.7,"dewptLow":9.3,"dewptAvg":9.5,"windchillHigh":10.9,"windchillLow":10.7,"windchillAvg":10.8,"heatindexHigh":10.9,"heatindexLow":10.7,"heatindexAvg":10.8,"pressureMax":1015.04,"pressureMin":1014.53,"pressureTrend":0.00,"precipRate":0.00,"precipTotal":0.00}},{"stationID":"ISTGBUCH2","tz":"Europe/London","obsTimeUtc":"2021-06-03T00:59:51Z","obsTimeLocal":"2021-06-03 01:59:51","epoch":1622681991,"lat":56.118,"lon":-4.301648,"solarRadiationHigh":0.0,"uvHigh":0.0,"winddirAvg":128,"humidityHigh":92.0,"humidityLow":91.0,"humidityAvg":91.2,"qcStatus":1,"metric":{"tempHigh":11.0,"tempLow":10.8,"tempAvg":10.9,"windspeedHigh":9.3,"windspeedLow":1.1,"windspeedAvg":5.3,"windgustHigh":13.0,"windgustLow":3.5,"windgustAvg":7.5,"dewptHigh":9.6,"dewptLow":9.4,"dewptAvg":9.5,"windchillHigh":11.0,"windchillLow":10.8,"windchillAvg":10.9,"heatindexHigh":11.0,"heatindexLow":10.8,"heatindexAvg":10.9,"pressureMax":1014.93,"pressureMin":1014.33,"pressureTrend":-0.61,"precipRate":0.00,"precipTotal":0.00}},{"stationID":"ISTGBUCH2","tz":"Europe/London","obsTimeUtc":"2021-06-03T01:59:51Z","obsTimeLocal":"2021-06-03 02:59:51","epoch":1622685591,"lat":56.118,"lon":-4.301648,"solarRadiationHigh":0.0,"uvHigh":0.0,"winddirAvg":137,"humidityHigh":92.0,"humidityLow":91.0,"humidityAvg":91.8,"qcStatus":1,"metric":{"tempHigh":11.2,"tempLow":11.0,"tempAvg":11.1,"windspeedHigh":10.8,"windspeedLow":1.1,"windspeedAvg":5.7,"windgustHigh":14.8,"windgustLow":1.8,"windgustAvg":7.9,"dewptHigh":10.0,"dewptLow":9.6,"dewptAvg":9.8,"windchillHigh":11.2,"windchillLow":11.0,"windchillAvg":11.1,"heatindexHigh":11.2,"heatindexLow":11.0,"heatindexAvg":11.1,"pressureMax":1014.73,"pressureMin":1014.02,"pressureTrend":-0.20,"precipRate":0.00,"precipTotal":0.00}},{"stationID":"ISTGBUCH2","tz":"Europe/London","obsTimeUtc":"2021-06-03T02:59:52Z","obsTimeLocal":"2021-06-03 03:59:52","epoch":1622689192,"lat":56.118,"lon":-4.301648,"solarRadiationHigh":0.0,"uvHigh":0.0,"winddirAvg":128,"humidityHigh":92.0,"humidityLow":91.0,"humidityAvg":91.7,"qcStatus":1,"metric":{"tempHigh":11.3,"tempLow":11.2,"tempAvg":11.3,"windspeedHigh":15.1,"windspeedLow":0.0,"windspeedAvg":5.4,"windgustHigh":20.1,"windgustLow":0.0,"windgustAvg":7.8,"dewptHigh":10.1,"dewptLow":9.8,"dewptAvg":10.0,"windchillHigh":11.3,"windchillLow":11.2,"windchillAvg":11.3,"heatindexHigh":11.3,"heatindexLow":11.2,"heatindexAvg":11.3,"pressureMax":1014.53,"pressureMin":1013.82,"pressureTrend":-0.10,"precipRate":0.00,"precipTotal":0.00}},{"stationID":"ISTGBUCH2","tz":"Europe/London","obsTimeUtc":"2021-06-03T03:59:52Z","obsTimeLocal":"2021-06-03 04:59:52","epoch":1622692792,"lat":56.118,"lon":-4.301648,"solarRadiationHigh":7.3,"uvHigh":0.0,"winddirAvg":131,"humidityHigh":92.0,"humidityLow":91.0,"humidityAvg":92.0,"qcStatus":1,"metric":{"tempHigh":11.2,"tempLow":11.2,"tempAvg":11.2,"windspeedHigh":10.1,"windspeedLow":0.6,"windspeedAvg":5.3,"windgustHigh":16.6,"windgustLow":1.8,"windgustAvg":7.6,"dewptHigh":10.0,"dewptLow":9.8,"dewptAvg":10.0,"windchillHigh":11.2,"windchillLow":11.2,"windchillAvg":11.2,"heatindexHigh":11.2,"heatindexLow":11.2,"heatindexAvg":11.2,"pressureMax":1014.43,"pressureMin":1013.82,"pressureTrend":0.10,"precipRate":0.00,"precipTotal":0.00}},{"stationID":"ISTGBUCH2","tz":"Europe/London","obsTimeUtc":"2021-06-03T04:59:52Z","obsTimeLocal":"2021-06-03 05:59:52","epoch":1622696392,"lat":56.118,"lon":-4.301648,"solarRadiationHigh":35.1,"uvHigh":0.0,"winddirAvg":134,"humidityHigh":91.0,"humidityLow":90.0,"humidityAvg":90.8,"qcStatus":1,"metric":{"tempHigh":11.4,"tempLow":11.2,"tempAvg":11.3,"windspeedHigh":13.7,"windspeedLow":1.4,"windspeedAvg":5.9,"windgustHigh":18.3,"windgustLow":1.8,"windgustAvg":8.6,"dewptHigh":10.0,"dewptLow":9.8,"dewptAvg":9.9,"windchillHigh":11.4,"windchillLow":11.2,"windchillAvg":11.3,"heatindexHigh":11.4,"heatindexLow":11.2,"heatindexAvg":11.3,"pressureMax":1014.22,"pressureMin":1013.82,"pressureTrend":-0.31,"precipRate":0.00,"precipTotal":0.00}},{"stationID":"ISTGBUCH2","tz":"Europe/London","obsTimeUtc":"2021-06-03T05:59:52Z","obsTimeLocal":"2021-06-03 06:59:52","epoch":1622699992,"lat":56.118,"lon":-4.301648,"solarRadiationHigh":28.6,"uvHigh":0.0,"winddirAvg":127,"humidityHigh":90.0,"humidityLow":88.0,"humidityAvg":89.3,"qcStatus":1,"metric":{"tempHigh":11.5,"tempLow":11.4,"tempAvg":11.4,"windspeedHigh":10.5,"windspeedLow":0.3,"windspeedAvg":4.7,"windgustHigh":14.8,"windgustLow":1.8,"windgustAvg":6.7,"dewptHigh":9.8,"dewptLow":9.4,"dewptAvg":9.7,"windchillHigh":11.5,"windchillLow":11.4,"windchillAvg":11.4,"heatindexHigh":11.5,"heatindexLow":11.4,"heatindexAvg":11.4,"pressureMax":1014.33,"pressureMin":1013.61,"pressureTrend":0.41,"precipRate":0.00,"precipTotal":0.00}},{"stationID":"ISTGBUCH2","tz":"Europe/London","obsTimeUtc":"2021-06-03T06:59:52Z","obsTimeLocal":"2021-06-03 07:59:52","epoch":1622703592,"lat":56.118,"lon":-4.301648,"solarRadiationHigh":48.1,"uvHigh":0.0,"winddirAvg":123,"humidityHigh":89.0,"humidityLow":88.0,"humidityAvg":88.5,"qcStatus":1,"metric":{"tempHigh":11.9,"tempLow":11.5,"tempAvg":11.8,"windspeedHigh":9.3,"windspeedLow":0.0,"windspeedAvg":3.9,"windgustHigh":13.0,"windgustLow":0.0,"windgustAvg":5.8,"dewptHigh":10.1,"dewptLow":9.5,"dewptAvg":9.9,"windchillHigh":11.9,"windchillLow":11.5,"windchillAvg":11.8,"heatindexHigh":11.9,"heatindexLow":11.5,"heatindexAvg":11.8,"pressureMax":1014.63,"pressureMin":1013.92,"pressureTrend":0.20,"precipRate":0.00,"precipTotal":0.00}},{"stationID":"ISTGBUCH2","tz":"Europe/London","obsTimeUtc":"2021-06-03T07:59:52Z","obsTimeLocal":"2021-06-03 08:59:52","epoch":1622707192,"lat":56.118,"lon":-4.301648,"solarRadiationHigh":78.1,"uvHigh":0.0,"winddirAvg":109,"humidityHigh":89.0,"humidityLow":87.0,"humidityAvg":88.0,"qcStatus":1,"metric":{"tempHigh":12.5,"tempLow":11.9,"tempAvg":12.3,"windspeedHigh":13.0,"windspeedLow":0.3,"windspeedAvg":5.3,"windgustHigh":18.3,"windgustLow":1.8,"windgustAvg":7.4,"dewptHigh":10.5,"dewptLow":10.0,"dewptAvg":10.3,"windchillHigh":12.5,"windchillLow":11.9,"windchillAvg":12.3,"heatindexHigh":12.5,"heatindexLow":11.9,"heatindexAvg":12.3,"pressureMax":1014.63,"pressureMin":1014.02,"pressureTrend":-0.10,"precipRate":0.00,"precipTotal":0.00}},{"stationID":"ISTGBUCH2","tz":"Europe/London","obsTimeUtc":"2021-06-03T08:59:52Z","obsTimeLocal":"2021-06-03 09:59:52","epoch":1622710792,"lat":56.118,"lon":-4.301648,"solarRadiationHigh":93.6,"uvHigh":0.0,"winddirAvg":120,"humidityHigh":92.0,"humidityLow":88.0,"humidityAvg":90.8,"qcStatus":1,"metric":{"tempHigh":12.5,"tempLow":12.1,"tempAvg":12.3,"windspeedHigh":9.3,"windspeedLow":0.3,"windspeedAvg":4.7,"windgustHigh":14.8,"windgustLow":1.8,"windgustAvg":6.9,"dewptHigh":11.1,"dewptLow":10.5,"dewptAvg":10.9,"windchillHigh":12.5,"windchillLow":12.1,"windchillAvg":12.3,"heatindexHigh":12.5,"heatindexLow":12.1,"heatindexAvg":12.3,"pressureMax":1014.83,"pressureMin":1014.02,"pressureTrend":0.20,"precipRate":1.80,"precipTotal":0.30}},{"stationID":"ISTGBUCH2","tz":"Europe/London","obsTimeUtc":"2021-06-03T09:59:52Z","obsTimeLocal":"2021-06-03 10:59:52","epoch":1622714392,"lat":56.118,"lon":-4.301648,"solarRadiationHigh":66.3,"uvHigh":0.0,"winddirAvg":129,"humidityHigh":93.0,"humidityLow":92.0,"humidityAvg":92.9,"qcStatus":1,"metric":{"tempHigh":12.3,"tempLow":12.0,"tempAvg":12.2,"windspeedHigh":8.7,"windspeedLow":0.3,"windspeedAvg":4.0,"windgustHigh":11.1,"windgustLow":1.8,"windgustAvg":5.6,"dewptHigh":11.2,"dewptLow":10.9,"dewptAvg":11.1,"windchillHigh":12.3,"windchillLow":12.0,"windchillAvg":12.2,"heatindexHigh":12.3,"heatindexLow":12.0,"heatindexAvg":12.2,"pressureMax":1014.83,"pressureMin":1014.22,"pressureTrend":-0.31,"precipRate":1.80,"precipTotal":0.51}},{"stationID":"ISTGBUCH2","tz":"Europe/London","obsTimeUtc":"2021-06-03T10:59:52Z","obsTimeLocal":"2021-06-03 11:59:52","epoch":1622717992,"lat":56.118,"lon":-4.301648,"solarRadiationHigh":514.4,"uvHigh":5.0,"winddirAvg":131,"humidityHigh":94.0,"humidityLow":87.0,"humidityAvg":92.3,"qcStatus":1,"metric":{"tempHigh":14.9,"tempLow":12.2,"tempAvg":13.2,"windspeedHigh":13.4,"windspeedLow":0.0,"windspeedAvg":4.0,"windgustHigh":16.6,"windgustLow":0.0,"windgustAvg":5.5,"dewptHigh":13.1,"dewptLow":11.1,"dewptAvg":12.0,"windchillHigh":14.9,"windchillLow":12.2,"windchillAvg":13.2,"heatindexHigh":14.9,"heatindexLow":12.2,"heatindexAvg":13.2,"pressureMax":1014.63,"pressureMin":1014.02,"pressureTrend":-0.10,"precipRate":1.19,"precipTotal":0.51}},{"stationID":"ISTGBUCH2","tz":"Europe/London","obsTimeUtc":"2021-06-03T11:59:52Z","obsTimeLocal":"2021-06-03 12:59:52","epoch":1622721592,"lat":56.118,"lon":-4.301648,"solarRadiationHigh":408.6,"uvHigh":4.0,"winddirAvg":123,"humidityHigh":88.0,"humidityLow":83.0,"humidityAvg":86.1,"qcStatus":1,"metric":{"tempHigh":15.7,"tempLow":14.4,"tempAvg":15.1,"windspeedHigh":10.5,"windspeedLow":0.0,"windspeedAvg":5.0,"windgustHigh":16.6,"windgustLow":0.0,"windgustAvg":7.0,"dewptHigh":13.4,"dewptLow":12.3,"dewptAvg":12.9,"windchillHigh":15.7,"windchillLow":14.4,"windchillAvg":15.1,"heatindexHigh":15.7,"heatindexLow":14.4,"heatindexAvg":15.1,"pressureMax":1014.33,"pressureMin":1013.72,"pressureTrend":-0.20,"precipRate":0.00,"precipTotal":0.51}},{"stationID":"ISTGBUCH2","tz":"Europe/London","obsTimeUtc":"2021-06-03T12:59:52Z","obsTimeLocal":"2021-06-03 13:59:52","epoch":1622725192,"lat":56.118,"lon":-4.301648,"solarRadiationHigh":212.1,"uvHigh":2.0,"winddirAvg":110,"humidityHigh":85.0,"humidityLow":80.0,"humidityAvg":82.3,"qcStatus":1,"metric":{"tempHigh":16.2,"tempLow":15.3,"tempAvg":15.8,"windspeedHigh":12.6,"windspeedLow":0.6,"windspeedAvg":5.2,"windgustHigh":18.3,"windgustLow":1.8,"windgustAvg":7.3,"dewptHigh":13.3,"dewptLow":12.4,"dewptAvg":12.8,"windchillHigh":16.2,"windchillLow":15.3,"windchillAvg":15.8,"heatindexHigh":16.2,"heatindexLow":15.3,"heatindexAvg":15.8,"pressureMax":1014.02,"pressureMin":1013.34,"pressureTrend":-0.41,"precipRate":0.00,"precipTotal":0.51}},{"stationID":"ISTGBUCH2","tz":"Europe/London","obsTimeUtc":"2021-06-03T13:59:52Z","obsTimeLocal":"2021-06-03 14:59:52","epoch":1622728792,"lat":56.118,"lon":-4.301648,"solarRadiationHigh":537.4,"uvHigh":5.0,"winddirAvg":108,"humidityHigh":82.0,"humidityLow":77.0,"humidityAvg":79.0,"qcStatus":1,"metric":{"tempHigh":17.8,"tempLow":16.2,"tempAvg":17.0,"windspeedHigh":16.9,"windspeedLow":1.4,"windspeedAvg":7.5,"windgustHigh":20.1,"windgustLow":3.5,"windgustAvg":10.4,"dewptHigh":14.0,"dewptLow":12.7,"dewptAvg":13.4,"windchillHigh":17.8,"windchillLow":16.2,"windchillAvg":17.0,"heatindexHigh":17.8,"heatindexLow":16.2,"heatindexAvg":17.0,"pressureMax":1013.72,"pressureMin":1012.84,"pressureTrend":-0.37,"precipRate":0.00,"precipTotal":0.51}},{"stationID":"ISTGBUCH2","tz":"Europe/London","obsTimeUtc":"2021-06-03T14:59:52Z","obsTimeLocal":"2021-06-03 15:59:52","epoch":1622732392,"lat":56.118,"lon":-4.301648,"solarRadiationHigh":278.4,"uvHigh":2.0,"winddirAvg":111,"humidityHigh":81.0,"humidityLow":77.0,"humidityAvg":78.8,"qcStatus":1,"metric":{"tempHigh":17.7,"tempLow":16.8,"tempAvg":17.3,"windspeedHigh":11.1,"windspeedLow":0.3,"windspeedAvg":5.2,"windgustHigh":21.9,"windgustLow":1.8,"windgustAvg":7.1,"dewptHigh":14.0,"dewptLow":13.3,"dewptAvg":13.6,"windchillHigh":17.7,"windchillLow":16.8,"windchillAvg":17.3,"heatindexHigh":17.7,"heatindexLow":16.8,"heatindexAvg":17.3,"pressureMax":1013.24,"pressureMin":1012.63,"pressureTrend":-0.20,"precipRate":0.00,"precipTotal":0.51}},{"stationID":"ISTGBUCH2","tz":"Europe/London","obsTimeUtc":"2021-06-03T15:59:52Z","obsTimeLocal":"2021-06-03 16:59:52","epoch":1622735992,"lat":56.118,"lon":-4.301648,"solarRadiationHigh":40.7,"uvHigh":0.0,"winddirAvg":99,"humidityHigh":84.0,"humidityLow":80.0,"humidityAvg":81.8,"qcStatus":1,"metric":{"tempHigh":16.8,"tempLow":16.3,"tempAvg":16.6,"windspeedHigh":6.1,"windspeedLow":0.0,"windspeedAvg":2.9,"windgustHigh":9.3,"windgustLow":0.0,"windgustAvg":3.8,"dewptHigh":13.7,"dewptLow":13.2,"dewptAvg":13.4,"windchillHigh":16.8,"windchillLow":16.3,"windchillAvg":16.6,"heatindexHigh":16.8,"heatindexLow":16.3,"heatindexAvg":16.6,"pressureMax":1013.24,"pressureMin":1012.73,"pressureTrend":0.00,"precipRate":0.00,"precipTotal":0.51}},{"stationID":"ISTGBUCH2","tz":"Europe/London","obsTimeUtc":"2021-06-03T16:59:52Z","obsTimeLocal":"2021-06-03 17:59:52","epoch":1622739592,"lat":56.118,"lon":-4.301648,"solarRadiationHigh":46.4,"uvHigh":0.0,"winddirAvg":4,"humidityHigh":89.0,"humidityLow":81.0,"humidityAvg":85.0,"qcStatus":1,"metric":{"tempHigh":16.7,"tempLow":15.3,"tempAvg":16.0,"windspeedHigh":4.3,"windspeedLow":0.0,"windspeedAvg":1.1,"windgustHigh":7.2,"windgustLow":0.0,"windgustAvg":1.8,"dewptHigh":13.8,"dewptLow":13.1,"dewptAvg":13.5,"windchillHigh":16.7,"windchillLow":15.3,"windchillAvg":16.0,"heatindexHigh":16.7,"heatindexLow":15.3,"heatindexAvg":16.0,"pressureMax":1013.41,"pressureMin":1012.84,"pressureTrend":0.20,"precipRate":0.00,"precipTotal":0.51}},{"stationID":"ISTGBUCH2","tz":"Europe/London","obsTimeUtc":"2021-06-03T17:59:52Z","obsTimeLocal":"2021-06-03 18:59:52","epoch":1622743192,"lat":56.118,"lon":-4.301648,"solarRadiationHigh":82.3,"uvHigh":0.0,"winddirAvg":317,"humidityHigh":89.0,"humidityLow":86.0,"humidityAvg":87.4,"qcStatus":1,"metric":{"tempHigh":15.8,"tempLow":14.9,"tempAvg":15.4,"windspeedHigh":5.0,"windspeedLow":0.0,"windspeedAvg":2.1,"windgustHigh":7.2,"windgustLow":0.0,"windgustAvg":2.8,"dewptHigh":13.8,"dewptLow":12.9,"dewptAvg":13.3,"windchillHigh":15.8,"windchillLow":14.9,"windchillAvg":15.4,"heatindexHigh":15.8,"heatindexLow":14.9,"heatindexAvg":15.4,"pressureMax":1013.82,"pressureMin":1013.04,"pressureTrend":0.37,"precipRate":0.00,"precipTotal":0.51}},{"stationID":"ISTGBUCH2","tz":"Europe/London","obsTimeUtc":"2021-06-03T18:59:52Z","obsTimeLocal":"2021-06-03 19:59:52","epoch":1622746792,"lat":56.118,"lon":-4.301648,"solarRadiationHigh":42.0,"uvHigh":0.0,"winddirAvg":326,"humidityHigh":88.0,"humidityLow":87.0,"humidityAvg":87.3,"qcStatus":1,"metric":{"tempHigh":15.1,"tempLow":14.8,"tempAvg":14.9,"windspeedHigh":4.0,"windspeedLow":0.0,"windspeedAvg":1.0,"windgustHigh":5.5,"windgustLow":0.0,"windgustAvg":1.6,"dewptHigh":13.0,"dewptLow":12.7,"dewptAvg":12.8,"windchillHigh":15.1,"windchillLow":14.8,"windchillAvg":14.9,"heatindexHigh":15.1,"heatindexLow":14.8,"heatindexAvg":14.9,"pressureMax":1013.92,"pressureMin":1013.34,"pressureTrend":0.41,"precipRate":0.00,"precipTotal":0.51}},{"stationID":"ISTGBUCH2","tz":"Europe/London","obsTimeUtc":"2021-06-03T19:59:52Z","obsTimeLocal":"2021-06-03 20:59:52","epoch":1622750392,"lat":56.118,"lon":-4.301648,"solarRadiationHigh":63.2,"uvHigh":0.0,"winddirAvg":7,"humidityHigh":88.0,"humidityLow":82.0,"humidityAvg":85.7,"qcStatus":1,"metric":{"tempHigh":16.2,"tempLow":14.4,"tempAvg":15.2,"windspeedHigh":5.8,"windspeedLow":0.0,"windspeedAvg":0.8,"windgustHigh":9.3,"windgustLow":0.0,"windgustAvg":1.3,"dewptHigh":13.2,"dewptLow":11.8,"dewptAvg":12.8,"windchillHigh":16.2,"windchillLow":14.4,"windchillAvg":15.2,"heatindexHigh":16.2,"heatindexLow":14.4,"heatindexAvg":15.2,"pressureMax":1013.92,"pressureMin":1013.51,"pressureTrend":-0.31,"precipRate":0.00,"precipTotal":0.51}},{"stationID":"ISTGBUCH2","tz":"Europe/London","obsTimeUtc":"2021-06-03T20:59:52Z","obsTimeLocal":"2021-06-03 21:59:52","epoch":1622753992,"lat":56.118,"lon":-4.301648,"solarRadiationHigh":16.9,"uvHigh":0.0,"winddirAvg":15,"humidityHigh":87.0,"humidityLow":81.0,"humidityAvg":83.1,"qcStatus":1,"metric":{"tempHigh":14.9,"tempLow":12.9,"tempAvg":14.4,"windspeedHigh":2.9,"windspeedLow":0.0,"windspeedAvg":0.4,"windgustHigh":3.5,"windgustLow":0.0,"windgustAvg":0.8,"dewptHigh":12.2,"dewptLow":10.7,"dewptAvg":11.5,"windchillHigh":14.9,"windchillLow":12.9,"windchillAvg":14.4,"heatindexHigh":14.9,"heatindexLow":12.9,"heatindexAvg":14.4,"pressureMax":1014.43,"pressureMin":1013.61,"pressureTrend":0.71,"precipRate":0.00,"precipTotal":0.51}},{"stationID":"ISTGBUCH2","tz":"Europe/London","obsTimeUtc":"2021-06-03T21:59:52Z","obsTimeLocal":"2021-06-03 22:59:52","epoch":1622757592,"lat":56.118,"lon":-4.301648,"solarRadiationHigh":0.9,"uvHigh":0.0,"winddirAvg":351,"humidityHigh":91.0,"humidityLow":87.0,"humidityAvg":88.5,"qcStatus":0,"metric":{"tempHigh":12.8,"tempLow":10.5,"tempAvg":11.5,"windspeedHigh":1.8,"windspeedLow":0.0,"windspeedAvg":0.1,"windgustHigh":1.8,"windgustLow":0.0,"windgustAvg":0.3,"dewptHigh":10.7,"dewptLow":8.9,"dewptAvg":9.7,"windchillHigh":12.8,"windchillLow":10.5,"windchillAvg":11.5,"heatindexHigh":12.8,"heatindexLow":10.5,"heatindexAvg":11.5,"pressureMax":1015.04,"pressureMin":1014.12,"pressureTrend":0.61,"precipRate":0.00,"precipTotal":0.51}},{"stationID":"ISTGBUCH2","tz":"Europe/London","obsTimeUtc":"2021-06-03T22:59:52Z","obsTimeLocal":"2021-06-03 23:59:52","epoch":1622761192,"lat":56.118,"lon":-4.301648,"solarRadiationHigh":0.0,"uvHigh":0.0,"winddirAvg":36,"humidityHigh":92.0,"humidityLow":89.0,"humidityAvg":90.5,"qcStatus":1,"metric":{"tempHigh":10.8,"tempLow":9.0,"tempAvg":10.1,"windspeedHigh":3.5,"windspeedLow":0.0,"windspeedAvg":0.5,"windgustHigh":3.5,"windgustLow":0.0,"windgustAvg":0.9,"dewptHigh":9.2,"dewptLow":7.8,"dewptAvg":8.6,"windchillHigh":10.8,"windchillLow":9.0,"windchillAvg":10.1,"heatindexHigh":10.8,"heatindexLow":9.0,"heatindexAvg":10.1,"pressureMax":1015.24,"pressureMin":1014.73,"pressureTrend":0.00,"precipRate":0.00,"precipTotal":0.51}}]}
