{"observations":[{"stationID":"ISTGBUCH2","tz":"Europe/London","obsTimeUtc":"2020-04-12T22:59:50Z","obsTimeLocal":"2020-04-12 23:59:50","epoch":1586732390,"lat":56.118,"lon":-4.301648,"solarRadiationHigh":881.9,"uvHigh":8.0,"winddirAvg":301,"humidityHigh":95.0,"humidityLow":46.0,"humidityAvg":75.0,"qcStatus":0,"metric":{"tempHigh":15.7,"tempLow":2.8,"tempAvg":9.1,"windspeedHigh":21.2,"windspeedLow":0.0,"windspeedAvg":4.5,"windgustHigh":27.7,"windgustLow":0.0,"windgustAvg":5.9,"dewptHigh":7.8,"dewptLow":-0.5,"dewptAvg":4.6,"windchillHigh":15.7,"windchillLow":1.6,"windchillAvg":8.8,"heatindexHigh":15.7,"heatindexLow":2.8,"heatindexAvg":9.1,"pressureMax":1024.72,"pressureMin":1010.84,"pressureTrend":0.49,"precipRate":0.00,"precipTotal":0.00}}]}
